ip_fetcher/__init__.py
ip_fetcher/ip_parser_phillip_bridgeman.py
ip_fetcher_phillip_bridgeman-5.6.dist-info/LICENSE
ip_fetcher_phillip_bridgeman-5.6.dist-info/METADATA
ip_fetcher_phillip_bridgeman-5.6.dist-info/WHEEL
ip_fetcher_phillip_bridgeman-5.6.dist-info/entry_points.txt
ip_fetcher_phillip_bridgeman-5.6.dist-info/top_level.txt
ip_fetcher_phillip_bridgeman-5.6.dist-info/RECORD
