Metadata-Version: 2.1
Name: ip_fetcher_phillip_bridgeman
Version: 5.6
Summary: A Python utility to fetch the current machine's public IP address.
Author: Phillip Bridgeman
Author-email: your.email@example.com
License-File: LICENSE
